[
    {
        "key": "dbln",
        "value": "%7B%2261551772411520%22%3A%22hy818PYB%22%2C%2261552675615820%22%3A%22e3Aj4XiD%22%2C%22100094327936579%22%3A%22AvG03PdK%22%2C%2261555351980782%22%3A%22YZeH7f3I%22%2C%2261556066933118%22%3A%22i1nFBbxy%22%2C%2261558928667113%22%3A%22SwoI8JKD%22%7D",
        "domain": "facebook.com",
        "path": "/login/device-based/",
        "hostOnly": false,
        "creation": "2024-05-05T15:58:00.549Z",
        "lastAccessed": "2024-05-05T15:58:00.550Z"
    },
    {
        "key": "datr",
        "value": "1FqYZf2Gvhio0yPJlcyRDwQ5",
        "domain": "facebook.com",
        "path": "/",
        "hostOnly": false,
        "creation": "2024-05-05T15:58:00.550Z",
        "lastAccessed": "2024-05-05T15:58:00.550Z"
    },
    {
        "key": "sb",
        "value": "1FqYZSfOtf53dNPvEGe0jyAr",
        "domain": "facebook.com",
        "path": "/",
        "hostOnly": false,
        "creation": "2024-05-05T15:58:00.550Z",
        "lastAccessed": "2024-05-05T15:58:00.550Z"
    },
    {
        "key": "vpd",
        "value": "v1%3B681x360x3",
        "domain": "facebook.com",
        "path": "/",
        "hostOnly": false,
        "creation": "2024-05-05T15:58:00.550Z",
        "lastAccessed": "2024-05-05T15:58:00.550Z"
    },
    {
        "key": "ps_n",
        "value": "1",
        "domain": "facebook.com",
        "path": "/",
        "hostOnly": false,
        "creation": "2024-05-05T15:58:00.550Z",
        "lastAccessed": "2024-05-05T15:58:00.550Z"
    },
    {
        "key": "ps_l",
        "value": "1",
        "domain": "facebook.com",
        "path": "/",
        "hostOnly": false,
        "creation": "2024-05-05T15:58:00.550Z",
        "lastAccessed": "2024-05-05T15:58:00.550Z"
    },
    {
        "key": "locale",
        "value": "en_GB",
        "domain": "facebook.com",
        "path": "/",
        "hostOnly": false,
        "creation": "2024-05-05T15:58:00.550Z",
        "lastAccessed": "2024-05-05T15:58:00.550Z"
    },
    {
        "key": "m_pixel_ratio",
        "value": "3",
        "domain": "facebook.com",
        "path": "/",
        "hostOnly": false,
        "creation": "2024-05-05T15:58:00.550Z",
        "lastAccessed": "2024-05-05T15:58:00.550Z"
    },
    {
        "key": "fr",
        "value": "0tY5Gs31xEZVEIErw.AWWTP9Gq2BsJvO7K6w7EIeSDIfw.BlmFrU..AAA.0.0.BmN6yq.AWUABPgSI7g",
        "domain": "facebook.com",
        "path": "/",
        "hostOnly": false,
        "creation": "2024-05-05T15:58:00.550Z",
        "lastAccessed": "2024-05-05T15:58:00.550Z"
    },
    {
        "key": "c_user",
        "value": "61556066933118",
        "domain": "facebook.com",
        "path": "/",
        "hostOnly": false,
        "creation": "2024-05-05T15:58:00.550Z",
        "lastAccessed": "2024-05-05T15:58:00.550Z"
    },
    {
        "key": "xs",
        "value": "4%3Ak_wcd2JcwlNM_A%3A2%3A1714924714%3A-1%3A10564",
        "domain": "facebook.com",
        "path": "/",
        "hostOnly": false,
        "creation": "2024-05-05T15:58:00.550Z",
        "lastAccessed": "2024-05-05T15:58:00.550Z"
    },
    {
        "key": "m_page_voice",
        "value": "61556066933118",
        "domain": "facebook.com",
        "path": "/",
        "hostOnly": false,
        "creation": "2024-05-05T15:58:00.550Z",
        "lastAccessed": "2024-05-05T15:58:00.550Z"
    },
    {
        "key": "wd",
        "value": "360x681",
        "domain": "facebook.com",
        "path": "/",
        "hostOnly": false,
        "creation": "2024-05-05T15:58:00.550Z",
        "lastAccessed": "2024-05-05T15:58:00.550Z"
    },
    {
        "key": "fbl_st",
        "value": "101331343%3BT%3A28582077",
        "domain": "facebook.com",
        "path": "/",
        "hostOnly": false,
        "creation": "2024-05-05T15:58:00.550Z",
        "lastAccessed": "2024-05-05T15:58:00.550Z"
    },
    {
        "key": "wl_cbv",
        "value": "v2%3Bclient_version%3A2492%3Btimestamp%3A1714924728",
        "domain": "facebook.com",
        "path": "/",
        "hostOnly": false,
        "creation": "2024-05-05T15:58:00.550Z",
        "lastAccessed": "2024-05-05T15:58:00.550Z"
    }
]
